AyonOpenAssetIOManager/__init__.py
AyonOpenAssetIOManager/ayon.py
AyonOpenAssetIOManager/ayon_traits/__init__.py
AyonOpenAssetIOManager/ayon_traits/core.py
AyonOpenAssetIOManager/ayon_traits/geo.py
AyonOpenAssetIOManager/ayon_traits/meta.py
AyonOpenAssetIOManager/ayon_traits/raster.py
AyonOpenAssetIOManager/ayon_traits/README.md
AyonOpenAssetIOManager/ayon_traits/scene.py
AyonOpenAssetIOManager/ayon_traits/sound.py
AyonOpenAssetIOManager/ayon_traits/time.py
AyonOpenAssetIOManager/AyonOpenAssetIOManagerInterface.py
LICENSE
poetry.lock
pyproject.toml
README.md
ayon_openassetio_manager_plugin-0.1.2.dist-info/entry_points.txt
ayon_openassetio_manager_plugin-0.1.2.dist-info/LICENSE
ayon_openassetio_manager_plugin-0.1.2.dist-info/METADATA
ayon_openassetio_manager_plugin-0.1.2.dist-info/WHEEL
ayon_openassetio_manager_plugin-0.1.2.dist-info/RECORD
